{
    "last_update": "2026-02-23 13:57:09",
    "coins": [
        {
            "name": "BTC",
            "price": 97126000.0,
            "rate": -2.4271161921600934
        },
        {
            "name": "XRP",
            "price": 2052.0,
            "rate": 0.04875670404680643
        },
        {
            "name": "ETH",
            "price": 2817000.0,
            "rate": -2.221450885109337
        },
        {
            "name": "DOGE",
            "price": 142.0,
            "rate": 0.7092198581560284
        },
        {
            "name": "SOL",
            "price": 118200.0,
            "rate": -3.114754098360656
        },
        {
            "name": "ZRX",
            "price": 153.0,
            "rate": -2.547770700636943
        },
        {
            "name": "ONDO",
            "price": 375.0,
            "rate": -2.849740932642487
        },
        {
            "name": "SUI",
            "price": 1328.0,
            "rate": -2.4246877296105804
        }
    ]
}